arrested/__init__.py
arrested/api.py
arrested/endpoint.py
arrested/exceptions.py
arrested/handlers.py
arrested/mixins.py
arrested/resource.py
arrested/contrib/__init__.py
arrested/contrib/kim_arrested.py
arrested/contrib/oauth.py
arrested/contrib/sql_alchemy.py
arrested-0.1.3.dist-info/METADATA
arrested-0.1.3.dist-info/RECORD
arrested-0.1.3.dist-info/WHEEL
arrested-0.1.3.dist-info/top_level.txt
tests/test_contrib/__init__.py
tests/test_contrib/test_kim.py
tests/test_contrib/test_sqlalchemy.py
